<?xml version="1.0" encoding="UTF-8"?>
<databaseChangeLog xmlns="http://www.liquibase.org/xml/ns/dbchangelog"
                   xmlns:xsi="http://www.w3.org/2001/XMLSchema-instance"
                   xsi:schemaLocation="http://www.liquibase.org/xml/ns/dbchangelog
                   https://www.liquibase.org/xml/ns/dbchangelog/dbchangelog-latest.xsd">

    <changeSet id="2" author="Quang Nguyen">
        <createTable tableName="CourseReview">
            <column name="Id" type="BIGINT" autoIncrement="true">
                <constraints primaryKey="true" nullable="false"/>
            </column>
            <column name="CourseId" type="BIGINT">
                <constraints nullable="false"/>
            </column>
            <column name="UserId" type="BIGINT">
                <constraints nullable="false"/>
            </column>
            <column name="Rating" type="int"/>
            <column name="Comment" type="VARCHAR(1000)"/>
            <column name="CreatedDate" type="TIMESTAMP WITHOUT TIME ZONE"/>
        </createTable>

        <addForeignKeyConstraint
                baseTableName="CourseReview"
                baseColumnNames="CourseId"
                referencedTableName="Course"
                referencedColumnNames="Id"
                constraintName="fk_coursereview_course"
        />

        <addForeignKeyConstraint
                baseTableName="CourseReview"
                baseColumnNames="UserId"
                referencedTableName="User"
                referencedColumnNames="Id"
                constraintName="fk_coursereview_user"
        />

    </changeSet>
</databaseChangeLog>